polyglot_turtle/__init__.py
polyglot_turtle/avrprog.py
polyglot_turtle/hidcborrpc.py
polyglot_turtle/polyglot_turtle.py
polyglot_turtle/tspl_label.py
polyglot_turtle/utils.py
polyglot_turtle-0.3.1.dist-info/LICENSE
polyglot_turtle-0.3.1.dist-info/METADATA
polyglot_turtle-0.3.1.dist-info/WHEEL
polyglot_turtle-0.3.1.dist-info/top_level.txt
polyglot_turtle-0.3.1.dist-info/RECORD
