Metadata-Version: 2.1
Name: polyglot-turtle
Version: 0.3.1
Summary: A python driver for the polyglot-turtle firmware
Home-page: https://github.com/jeremyherbert/python-polyglot-turtle
Author: Jeremy Herbert
Author-email: jeremy.006@gmail.com
Project-URL: Bug Tracker, https://github.com/jeremyherbert/python-polyglot-turtle/issues
Classifier: Programming Language :: Python :: 3
Classifier: License :: OSI Approved :: MIT License
Classifier: Operating System :: OS Independent
Requires-Python: >=3.6
License-File: LICENSE
Requires-Dist: setuptools >=42
Requires-Dist: wheel
Requires-Dist: hidapi
Requires-Dist: cbor2
Requires-Dist: packaging
Requires-Dist: simplehdlc
